perturbnet/__init__.py
perturbnet/util.py
perturbnet/baselines/__init__.py
perturbnet/baselines/knn.py
perturbnet/baselines/linear.py
perturbnet/chemicalvae/__init__.py
perturbnet/chemicalvae/chemicalVAE.py
perturbnet/cinn/FeatureAttr.py
perturbnet/cinn/__init__.py
perturbnet/cinn/flow.py
perturbnet/cinn/flow_generate.py
perturbnet/data_vae/__init__.py
perturbnet/data_vae/util.py
perturbnet/data_vae/vae.py
perturbnet/genotypevae/__init__.py
perturbnet/genotypevae/genotypeVAE.py
perturbnet/net2net/__init__.py
perturbnet/net2net/ckpt_util.py
perturbnet/net2net/data/__init__.py
perturbnet/net2net/data/base.py
perturbnet/net2net/data/coco.py
perturbnet/net2net/data/faces.py
perturbnet/net2net/data/utils.py
perturbnet/net2net/data/zcodes.py
perturbnet/net2net/models/__init__.py
perturbnet/net2net/models/autoencoder.py
perturbnet/net2net/models/flows/__init__.py
perturbnet/net2net/models/flows/flow.py
perturbnet/net2net/models/flows/scviflow.py
perturbnet/net2net/models/flows/util.py
perturbnet/net2net/modules/__init__.py
perturbnet/net2net/modules/util.py
perturbnet/net2net/modules/autoencoder/__init__.py
perturbnet/net2net/modules/autoencoder/basic.py
perturbnet/net2net/modules/autoencoder/decoder.py
perturbnet/net2net/modules/autoencoder/encoder.py
perturbnet/net2net/modules/autoencoder/loss.py
perturbnet/net2net/modules/autoencoder/lpips.py
perturbnet/net2net/modules/captions/__init__.py
perturbnet/net2net/modules/captions/model.py
perturbnet/net2net/modules/captions/models.py
perturbnet/net2net/modules/discriminator/__init__.py
perturbnet/net2net/modules/discriminator/model.py
perturbnet/net2net/modules/distributions/__init__.py
perturbnet/net2net/modules/distributions/distributions.py
perturbnet/net2net/modules/facenet/__init__.py
perturbnet/net2net/modules/facenet/inception_resnet_v1.py
perturbnet/net2net/modules/facenet/model.py
perturbnet/net2net/modules/flow/__init__.py
perturbnet/net2net/modules/flow/base.py
perturbnet/net2net/modules/flow/blocks.py
PerturbNet-0.0.3.dist-info/LICENSE
PerturbNet-0.0.3.dist-info/METADATA
PerturbNet-0.0.3.dist-info/WHEEL
PerturbNet-0.0.3.dist-info/top_level.txt
PerturbNet-0.0.3.dist-info/RECORD
