Metadata-Version: 2.1
Name: PerturbNet
Version: 0.0.3
Summary: PerturbNet
Home-page: https://github.com/welch-lab/PerturbNet
Author: Hengshi Yu, Weizhou Qian, Yuxuan Song, Joshua Welch
License: GPL-3.0
Platform: UNKNOWN
Requires-Python: >=3.7,<3.8
License-File: LICENSE
Requires-Dist: scvi-tools (==0.7.1)
Requires-Dist: tensorflow (==1.15.0)
Requires-Dist: torch (==1.13.1)
Requires-Dist: umap-learn (==0.4.6)
Requires-Dist: numpy (==1.19.5)
Requires-Dist: torchvision (==0.2.0)
Requires-Dist: numba (==0.49.1)
Requires-Dist: llvmlite (==0.32.1)
Requires-Dist: captum (==0.7.0)
Requires-Dist: rdkit
Requires-Dist: pickle5
Requires-Dist: scikit-learn
Requires-Dist: scipy
Requires-Dist: scanpy
Requires-Dist: tqdm
Requires-Dist: seaborn
Requires-Dist: fair-esm
Requires-Dist: requests
Requires-Dist: plotnine
